IQA_Metrics_Toolbox/__init__.py
IQA_Metrics_Toolbox/brisque.py
IQA_Metrics_Toolbox/brisque_test.py
IQA_Metrics_Toolbox/niqe.py
IQA_Metrics_Toolbox/psnr.py
IQA_Metrics_Toolbox/ssim.py
IQA_Metrics_Toolbox/brisque_models/__init__.py
IQA_Metrics_Toolbox/brisque_models/normalize.pickle
IQA_Metrics_Toolbox/brisque_models/svm.txt
IQA_Metrics_Toolbox/niqe_model/niqe_params.mat
IQA_Metrics_Toolbox-2023.0.8.dist-info/LICENSE.txt
IQA_Metrics_Toolbox-2023.0.8.dist-info/METADATA
IQA_Metrics_Toolbox-2023.0.8.dist-info/WHEEL
IQA_Metrics_Toolbox-2023.0.8.dist-info/top_level.txt
IQA_Metrics_Toolbox-2023.0.8.dist-info/RECORD
